itkwasm_dicom/__init__.py
itkwasm_dicom/_version.py
itkwasm_dicom/apply_presentation_state_to_image.py
itkwasm_dicom/apply_presentation_state_to_image_async.py
itkwasm_dicom/read_dicom_encapsulated_pdf.py
itkwasm_dicom/read_dicom_encapsulated_pdf_async.py
itkwasm_dicom/read_image_dicom_file_series.py
itkwasm_dicom/read_image_dicom_file_series_async.py
itkwasm_dicom/read_overlapping_segmentation.py
itkwasm_dicom/read_overlapping_segmentation_async.py
itkwasm_dicom/read_segmentation.py
itkwasm_dicom/read_segmentation_async.py
itkwasm_dicom/structured_report_to_html.py
itkwasm_dicom/structured_report_to_html_async.py
itkwasm_dicom/structured_report_to_text.py
itkwasm_dicom/structured_report_to_text_async.py
itkwasm_dicom/write_multi_segmentation.py
itkwasm_dicom/write_multi_segmentation_async.py
itkwasm_dicom/write_overlapping_segmentation.py
itkwasm_dicom/write_overlapping_segmentation_async.py
itkwasm_dicom/write_rt_struct.py
itkwasm_dicom/write_rt_struct_async.py
itkwasm_dicom/write_segmentation.py
itkwasm_dicom/write_segmentation_async.py
itkwasm_dicom-7.6.4.dist-info/METADATA
itkwasm_dicom-7.6.4.dist-info/WHEEL
itkwasm_dicom-7.6.4.dist-info/RECORD
